[{"city":"Acworth","slug":"acworth-ga","state":"GA","zip_codes":["30144","30101"]},{"city":"Albany","slug":"albany-ga","state":"GA","zip_codes":["31705","31721","31701","31707","31702","31703","31706","31708"]},{"city":"Alpharetta","slug":"alpharetta-ga","state":"GA","zip_codes":["30022","30004","30005","30009","30023"]},{"city":"Athens","slug":"athens-ga","state":"GA","zip_codes":["30602","30622","30601","30605","30606","30607","30609","30683","30603","30608"]},{"city":"Brunswick","slug":"brunswick-ga","state":"GA","zip_codes":["31520","31521"]},{"city":"Candler-McAfee","slug":"candler-mcafee-ga","state":"GA","zip_codes":["30032"]},{"city":"Canton","slug":"canton-ga","state":"GA","zip_codes":["30114","30115"]},{"city":"Carrollton","slug":"carrollton-ga","state":"GA","zip_codes":["30118","30116","30117","30109","30112"]},{"city":"Cartersville","slug":"cartersville-ga","state":"GA","zip_codes":["30121","30120"]},{"city":"Dalton","slug":"dalton-ga","state":"GA","zip_codes":["30721","30720","30719","30722"]},{"city":"Denton","slug":"denton-ga","state":"GA","zip_codes":["31532"]},{"city":"Douglasville","slug":"douglasville-ga","state":"GA","zip_codes":["30134","30135","30122","30133","30154"]},{"city":"Dublin","slug":"dublin-ga","state":"GA","zip_codes":["31021","31040"]},{"city":"Duluth","slug":"duluth-ga","state":"GA","zip_codes":["30097","30096","30098"]},{"city":"East Point","slug":"east-point-ga","state":"GA","zip_codes":["30344","30349","30364","30385"]},{"city":"Evans","slug":"evans-ga","state":"GA","zip_codes":["30809"]},{"city":"Gainesville","slug":"gainesville-ga","state":"GA","zip_codes":["30501","30507","30504"]},{"city":"Griffin","slug":"griffin-ga","state":"GA","zip_codes":["30224","30223"]},{"city":"Hinesville","slug":"hinesville-ga","state":"GA","zip_codes":["31313","31310"]},{"city":"Johns Creek","slug":"johns-creek-ga","state":"GA","zip_codes":["30022","30097","30005"]},{"city":"Kennesaw","slug":"kennesaw-ga","state":"GA","zip_codes":["30144","30152"]},{"city":"Lawrenceville","slug":"lawrenceville-ga","state":"GA","zip_codes":["30046","30049"]},{"city":"Mableton","slug":"mableton-ga","state":"GA","zip_codes":["30126","30106","30082","30168"]},{"city":"Marietta","slug":"marietta-ga","state":"GA","zip_codes":["30090","30060","30062","30064","30067","30008","30006","30007"]},{"city":"Martinez","slug":"martinez-ga","state":"GA","zip_codes":["30907","30809"]},{"city":"McDonough","slug":"mcdonough-ga","state":"GA","zip_codes":["30253","30252"]},{"city":"Milton","slug":"milton-ga","state":"GA","zip_codes":["30004","30009"]},{"city":"Newnan","slug":"newnan-ga","state":"GA","zip_codes":["30263","30265","30264","30271"]},{"city":"Peachtree City","slug":"peachtree-city-ga","state":"GA","zip_codes":["30269","31169"]},{"city":"Peachtree Corners","slug":"peachtree-corners-ga","state":"GA","zip_codes":["30071","30092","30360","30010"]},{"city":"Perry","slug":"perry-ga","state":"GA","zip_codes":["31069"]},{"city":"Pooler","slug":"pooler-ga","state":"GA","zip_codes":["31322"]},{"city":"Redan","slug":"redan-ga","state":"GA","zip_codes":["30058","30088","30074"]},{"city":"Rome","slug":"rome-ga","state":"GA","zip_codes":["30161","30165","30162","30164"]},{"city":"Roswell","slug":"roswell-ga","state":"GA","zip_codes":["30075","30076","30077"]},{"city":"Sandy Springs","slug":"sandy-springs-ga","state":"GA","zip_codes":["30350","30327","30328","30342","30358","31150","31156"]},{"city":"Savannah","slug":"savannah-ga","state":"GA","zip_codes":["31302","31409","31408","31401","31405","31404","31407","31406","31421","31419","31415","31403","31412","31416","31418","31420"]},{"city":"Smyrna","slug":"smyrna-ga","state":"GA","zip_codes":["30126","30082","30080","30081"]},{"city":"Snellville","slug":"snellville-ga","state":"GA","zip_codes":["30078"]},{"city":"South Fulton","slug":"south-fulton-ga","state":"GA","zip_codes":["30336","30331","30272","30349","30291","30296","30213","30378","31131","31136"]},{"city":"Statesboro","slug":"statesboro-ga","state":"GA","zip_codes":["30460","30461","30458","30459"]},{"city":"Stockbridge","slug":"stockbridge-ga","state":"GA","zip_codes":["30253","30281"]},{"city":"Stonecrest","slug":"stonecrest-ga","state":"GA","zip_codes":["30038","30035","30058"]},{"city":"Sugar Hill","slug":"sugar-hill-ga","state":"GA","zip_codes":["30518"]},{"city":"Suwanee","slug":"suwanee-ga","state":"GA","zip_codes":["30024"]},{"city":"Tifton","slug":"tifton-ga","state":"GA","zip_codes":["31793","31794"]},{"city":"Tucker","slug":"tucker-ga","state":"GA","zip_codes":["30087","30084","30083","30085"]},{"city":"Union City","slug":"union-city-ga","state":"GA","zip_codes":["30349","30291","30213","31192"]},{"city":"Valdosta","slug":"valdosta-ga","state":"GA","zip_codes":["31698","31602","31601","31605","31603","31604"]},{"city":"Warner Robins","slug":"warner-robins-ga","state":"GA","zip_codes":["31088","31005","31093","31099"]},{"city":"Waycross","slug":"waycross-ga","state":"GA","zip_codes":["31501","31503","31502"]},{"city":"Woodstock","slug":"woodstock-ga","state":"GA","zip_codes":["30189","30188"]}]