[{"city":"Bellevue","slug":"bellevue-ne","state":"NE","zip_codes":["68147","68123","68005","68157"]},{"city":"Columbus","slug":"columbus-ne","state":"NE","zip_codes":["68601","68602"]},{"city":"Fremont","slug":"fremont-ne","state":"NE","zip_codes":["68025","68026"]},{"city":"Grand Island","slug":"grand-island-ne","state":"NE","zip_codes":["68803","68801"]},{"city":"Hastings","slug":"hastings-ne","state":"NE","zip_codes":["68901","68902"]},{"city":"Kearney","slug":"kearney-ne","state":"NE","zip_codes":["68847","68845","68849","68848"]},{"city":"Martell","slug":"martell-ne","state":"NE","zip_codes":["68404"]},{"city":"Norfolk","slug":"norfolk-ne","state":"NE","zip_codes":["68701","68702"]},{"city":"North Platte","slug":"north-platte-ne","state":"NE","zip_codes":["69101","69103"]},{"city":"Papillion","slug":"papillion-ne","state":"NE","zip_codes":["68046","68128","68133","68138"]}]