[{"city":"Arlington","slug":"arlington-wa","state":"WA","zip_codes":["98223"]},{"city":"Auburn","slug":"auburn-wa","state":"WA","zip_codes":["98001","98002","98092"]},{"city":"Bainbridge Island","slug":"bainbridge-island-wa","state":"WA","zip_codes":["98110","98061"]},{"city":"Battle Ground","slug":"battle-ground-wa","state":"WA","zip_codes":["98604"]},{"city":"Bellingham","slug":"bellingham-wa","state":"WA","zip_codes":["98225","98226","98229","98228"]},{"city":"Bonney Lake","slug":"bonney-lake-wa","state":"WA","zip_codes":["98391"]},{"city":"Bothell","slug":"bothell-wa","state":"WA","zip_codes":["98021","98011","98041"]},{"city":"Camas","slug":"camas-wa","state":"WA","zip_codes":["98607"]},{"city":"Cottage Lake","slug":"cottage-lake-wa","state":"WA","zip_codes":["98072","98077"]},{"city":"Covington","slug":"covington-wa","state":"WA","zip_codes":["98042"]},{"city":"Duvall","slug":"duvall-wa","state":"WA","zip_codes":["98019"]},{"city":"Eatonville","slug":"eatonville-wa","state":"WA","zip_codes":["98328"]},{"city":"Ellensburg","slug":"ellensburg-wa","state":"WA","zip_codes":["98926"]},{"city":"Everett","slug":"everett-wa","state":"WA","zip_codes":["98207","98204","98203","98201","98208","98206","98213"]},{"city":"Five Corners","slug":"five-corners-wa","state":"WA","zip_codes":["98662"]},{"city":"Frederickson","slug":"frederickson-wa","state":"WA","zip_codes":["98387","98375","98446"]},{"city":"Graham","slug":"graham-wa","state":"WA","zip_codes":["98338"]},{"city":"Issaquah","slug":"issaquah-wa","state":"WA","zip_codes":["98029","98027"]},{"city":"Kenmore","slug":"kenmore-wa","state":"WA","zip_codes":["98028"]},{"city":"Lacey","slug":"lacey-wa","state":"WA","zip_codes":["98513","98516","98503","98509"]},{"city":"Lakewood","slug":"lakewood-wa","state":"WA","zip_codes":["98499","98498","98496","98497"]},{"city":"Longview","slug":"longview-wa","state":"WA","zip_codes":["98632"]},{"city":"Marysville","slug":"marysville-wa","state":"WA","zip_codes":["98271","98270"]},{"city":"Moses Lake","slug":"moses-lake-wa","state":"WA","zip_codes":["98837"]},{"city":"Mount Vernon","slug":"mount-vernon-wa","state":"WA","zip_codes":["98274","98273"]},{"city":"Mukilteo","slug":"mukilteo-wa","state":"WA","zip_codes":["98275"]},{"city":"Oak Harbor","slug":"oak-harbor-wa","state":"WA","zip_codes":["98277"]},{"city":"Pasco","slug":"pasco-wa","state":"WA","zip_codes":["99301","99302"]},{"city":"Port Angeles","slug":"port-angeles-wa","state":"WA","zip_codes":["98363","98362"]},{"city":"Pullman","slug":"pullman-wa","state":"WA","zip_codes":["99163","99164"]},{"city":"Puyallup","slug":"puyallup-wa","state":"WA","zip_codes":["98374","98371","98372","98373","98352"]},{"city":"Richland","slug":"richland-wa","state":"WA","zip_codes":["99352","99354"]},{"city":"Salmon Creek","slug":"salmon-creek-wa","state":"WA","zip_codes":["98686","98685"]},{"city":"Sammamish","slug":"sammamish-wa","state":"WA","zip_codes":["98029","98075","98074"]},{"city":"SeaTac","slug":"seatac-wa","state":"WA","zip_codes":["98158","98148","98198","98168","98188","98131"]},{"city":"Silver Firs","slug":"silver-firs-wa","state":"WA","zip_codes":["98296","98012","98208"]},{"city":"Silverdale","slug":"silverdale-wa","state":"WA","zip_codes":["98311","98383","98370"]},{"city":"South Hill","slug":"south-hill-wa","state":"WA","zip_codes":["98374","98375","98373"]},{"city":"Spokane Valley","slug":"spokane-valley-wa","state":"WA","zip_codes":["99206","99016","99212","99216","99037","99211","99213","99215"]},{"city":"Stanwood","slug":"stanwood-wa","state":"WA","zip_codes":["98292"]},{"city":"Tukwila","slug":"tukwila-wa","state":"WA","zip_codes":["98108","98178","98168","98188","98138","98190"]},{"city":"Tumwater","slug":"tumwater-wa","state":"WA","zip_codes":["98501","98512","98511"]},{"city":"Union Hill-Novelty Hill","slug":"union-hill-novelty-hill-wa","state":"WA","zip_codes":["98053","98077"]},{"city":"Walla Walla","slug":"walla-walla-wa","state":"WA","zip_codes":["99362"]},{"city":"Wenatchee","slug":"wenatchee-wa","state":"WA","zip_codes":["98801"]},{"city":"Yakima","slug":"yakima-wa","state":"WA","zip_codes":["98901","98903","98902","98908","98904","98907"]},{"city":"Yelm","slug":"yelm-wa","state":"WA","zip_codes":["98576","98597"]}]